georges_core/__init__.py
georges_core/codes_io/__init__.py
georges_core/codes_io/csv.py
georges_core/codes_io/mad.py
georges_core/codes_io/transport.py
georges_core/distribution.py
georges_core/frame.py
georges_core/geometry.py
georges_core/kinematics.py
georges_core/madx/__init__.py
georges_core/madx/madx.py
georges_core/particles.py
georges_core/patchable.py
georges_core/sequences/__init__.py
georges_core/sequences/betablock.py
georges_core/sequences/elements.py
georges_core/sequences/sequence.py
georges_core/twiss.py
georges_core/units.py
georges_core/utils.py
georges_core/vis/__init__.py
georges_core/vis/artist.py
georges_core/vis/gnuplot.py
georges_core/vis/matplotlib.py
georges_core/vis/plotly.py
georges_core/vis/vtk_utils.py
georges_core-2023.3.dist-info/LICENSE
georges_core-2023.3.dist-info/METADATA
georges_core-2023.3.dist-info/WHEEL
georges_core-2023.3.dist-info/RECORD
