Metadata-Version: 2.1
Name: georges-core
Version: 2023.3
Summary: Georges' accelerator physics library - Core
Author: Cédric Hernalsteens
Author-email: cedric.hernalsteens@ulb.be
Requires-Python: >3.9,<3.11
Classifier: Programming Language :: Python :: 3
Classifier: Programming Language :: Python :: 3.10
Requires-Dist: Pint (==0.22)
Requires-Dist: PyYAML (==6.0.1)
Requires-Dist: awkward (==2.5.0)
Requires-Dist: awkward-pandas (==2023.8.0)
Requires-Dist: boost-histogram (==1.4.0)
Requires-Dist: cpymad (==1.14.2)
Requires-Dist: fastparquet (==2023.10.1)
Requires-Dist: ipykernel (==6.27.1)
Requires-Dist: ipyparallel (==8.6.1)
Requires-Dist: jupyterlab (==4.0.9)
Requires-Dist: jupyterlab-code-formatter (==2.2.1)
Requires-Dist: matplotlib (==3.8.2)
Requires-Dist: mergedeep (==1.3.4)
Requires-Dist: nbdime (==4.0.1)
Requires-Dist: numba (==0.56.3)
Requires-Dist: numpy (==1.22.3)
Requires-Dist: numpy-quaternion (==2022.4.4)
Requires-Dist: pandas (==1.5.1)
Requires-Dist: plotly (==5.18.0)
Requires-Dist: pyarrow (==14.0.1)
Requires-Dist: pybdsim (==3.5.1)
Requires-Dist: scipy (==1.7.3)
Requires-Dist: uproot (==5.1.2)
Requires-Dist: vtk (==9.3.0)
